Metadata-Version: 2.1
Name: yoloxdetect
Version: 0.0.6
Summary: It is a demo application of the YOLOX model.
Home-page: https://github.com/kadirnar/yolox-pip
Author: kadirnar
License: MIT
Keywords: machine-learning,deep-learning,pytorch,vision,image-classification,object-detection,yolox,yolov7,yolov6,yolo detector,yolov5
Classifier: Development Status :: 5 - Production/Stable
Classifier: Operating System :: OS Independent
Classifier: Intended Audience :: Developers
Classifier: Intended Audience :: Science/Research
Classifier: Programming Language :: Python :: 3
Classifier: Programming Language :: Python :: 3.7
Classifier: Programming Language :: Python :: 3.8
Classifier: Programming Language :: Python :: 3.9
Classifier: Topic :: Software Development :: Libraries
Classifier: Topic :: Software Development :: Libraries :: Python Modules
Classifier: Topic :: Education
Classifier: Topic :: Scientific/Engineering
Classifier: Topic :: Scientific/Engineering :: Artificial Intelligence
Requires-Python: >=3.6
License-File: LICENSE
